[
  {
    "aliases": null,
    "resourceType": "kubernetesVersions",
    "apiVersions": [
      "2024-01-01",
      "2023-11-15-preview"
    ],
    "locations": [
      "Australia East",
      "Central India",
      "East US",
      "South Central US",
      "Southeast Asia",
      "West Europe",
      "West US 3"
    ],
    "zoneMappings": []
  },
  {
    "aliases": null,
    "resourceType": "Locations",
    "apiVersions": [
      "2024-01-01",
      "2023-11-15-preview",
      "2023-11-01",
      "2022-09-01-preview",
      "2022-05-01-preview",
      "2022-01-01-preview",
      "2021-09-01-preview",
      "2021-08-01-preview"
    ],
    "locations": [],
    "zoneMappings": []
  },
  {
    "aliases": null,
    "resourceType": "Locations/operationStatuses",
    "apiVersions": [
      "2024-01-01",
      "2023-11-15-preview",
      "2023-11-01",
      "2022-09-01-preview",
      "2022-05-01-preview",
      "2022-01-01-preview",
      "2021-09-01-preview",
      "2021-08-01-preview"
    ],
    "locations": [
      "Australia East",
      "Central India",
      "East US",
      "East US 2 EUAP",
      "South Central US",
      "Southeast Asia",
      "West Europe",
      "West US 3"
    ],
    "zoneMappings": []
  },
  {
    "aliases": null,
    "resourceType": "Operations",
    "apiVersions": [
      "2024-01-01",
      "2023-11-15-preview",
      "2023-11-01",
      "2022-09-01-preview",
      "2022-05-01-preview",
      "2022-01-01-preview",
      "2021-09-01-preview",
      "2021-08-01-preview"
    ],
    "locations": [],
    "zoneMappings": []
  },
  {
    "aliases": null,
    "resourceType": "provisionedClusterInstances",
    "apiVersions": [
      "2024-01-01",
      "2023-11-15-preview"
    ],
    "locations": [
      "Australia East",
      "Central India",
      "East US",
      "South Central US",
      "Southeast Asia",
      "West Europe",
      "West US 3"
    ],
    "zoneMappings": []
  },
  {
    "aliases": null,
    "resourceType": "provisionedClusters",
    "apiVersions": [
      "2022-09-01-preview",
      "2022-05-01-preview",
      "2022-01-01-preview",
      "2021-09-01-preview",
      "2021-08-01-preview"
    ],
    "locations": [
      "East US",
      "South Central US",
      "West Europe",
      "West US 3"
    ],
    "zoneMappings": []
  },
  {
    "aliases": null,
    "resourceType": "provisionedClusters/agentPools",
    "apiVersions": [
      "2022-09-01-preview",
      "2022-05-01-preview",
      "2022-01-01-preview"
    ],
    "locations": [
      "East US",
      "South Central US",
      "West Europe",
      "West US 3"
    ],
    "zoneMappings": []
  },
  {
    "aliases": null,
    "resourceType": "provisionedClusters/hybridIdentityMetadata",
    "apiVersions": [
      "2022-09-01-preview",
      "2022-05-01-preview",
      "2022-01-01-preview",
      "2021-09-01-preview"
    ],
    "locations": [
      "East US",
      "South Central US",
      "West Europe",
      "West US 3"
    ],
    "zoneMappings": []
  },
  {
    "aliases": null,
    "resourceType": "provisionedClusters/upgradeProfiles",
    "apiVersions": [
      "2022-09-01-preview"
    ],
    "locations": [
      "East US",
      "South Central US",
      "West Europe",
      "West US 3"
    ],
    "zoneMappings": []
  },
  {
    "aliases": null,
    "resourceType": "skus",
    "apiVersions": [
      "2024-01-01",
      "2023-11-15-preview"
    ],
    "locations": [
      "Australia East",
      "Central India",
      "East US",
      "South Central US",
      "Southeast Asia",
      "West Europe",
      "West US 3"
    ],
    "zoneMappings": []
  },
  {
    "aliases": null,
    "resourceType": "virtualNetworks",
    "apiVersions": [
      "2024-01-01",
      "2023-11-15-preview"
    ],
    "locations": [
      "Australia East",
      "Central India",
      "East US",
      "South Central US",
      "Southeast Asia",
      "West Europe",
      "West US 3"
    ],
    "zoneMappings": []
  }
]
