[
  {
    "aliases": null,
    "resourceType": "locations",
    "apiVersions": [
      "2022-09-01",
      "2022-06-01",
      "2020-09-01",
      "2020-03-01",
      "2019-10-01",
      "2019-06-01",
      "2019-03-01",
      "2019-02-01",
      "2018-10-01",
      "2018-07-01",
      "2018-04-02"
    ],
    "locations": [],
    "zoneMappings": []
  },
  {
    "aliases": null,
    "resourceType": "locations/checkNameAvailability",
    "apiVersions": [
      "2022-09-01",
      "2022-06-01",
      "2020-09-01",
      "2020-03-01",
      "2019-10-01",
      "2019-06-01",
      "2019-03-01",
      "2019-02-01",
      "2018-10-01",
      "2018-07-01",
      "2018-04-02"
    ],
    "locations": [
      "Australia East",
      "Australia Southeast",
      "Brazil South",
      "Canada Central",
      "Canada East",
      "Central India",
      "Central US",
      "East Asia",
      "East US",
      "East US 2",
      "France Central",
      "France South",
      "Germany North",
      "Germany West Central",
      "italy north",
      "Japan East",
      "Japan West",
      "Korea Central",
      "Korea South",
      "North Central US",
      "North Europe",
      "Norway East",
      "Norway West",
      "South Africa North",
      "South Africa West",
      "South Central US",
      "South India",
      "Southeast Asia",
      "Sweden Central",
      "Switzerland North",
      "Switzerland West",
      "UAE Central",
      "UAE North",
      "UK South",
      "UK West",
      "West Central US",
      "West Europe",
      "West US",
      "West US 2",
      "West US 3"
    ],
    "zoneMappings": []
  },
  {
    "aliases": null,
    "resourceType": "locations/operationResults",
    "apiVersions": [
      "2022-09-01",
      "2022-06-01",
      "2020-09-01",
      "2020-03-01"
    ],
    "locations": [
      "Australia East",
      "Australia Southeast",
      "Brazil South",
      "Canada Central",
      "Canada East",
      "Central India",
      "Central US",
      "East Asia",
      "East US",
      "East US 2",
      "France Central",
      "France South",
      "Germany North",
      "Germany West Central",
      "italy north",
      "Japan East",
      "Japan West",
      "Korea Central",
      "Korea South",
      "North Central US",
      "North Europe",
      "Norway East",
      "Norway West",
      "South Africa North",
      "South Africa West",
      "South Central US",
      "South India",
      "Southeast Asia",
      "Sweden Central",
      "Switzerland North",
      "Switzerland West",
      "UAE Central",
      "UAE North",
      "UK South",
      "UK West",
      "West Central US",
      "West Europe",
      "West US",
      "West US 2",
      "West US 3"
    ],
    "zoneMappings": []
  },
  {
    "aliases": null,
    "resourceType": "locations/operations",
    "apiVersions": [
      "2022-09-01",
      "2022-06-01",
      "2020-09-01",
      "2020-03-01"
    ],
    "locations": [
      "Australia East",
      "Australia Southeast",
      "Brazil South",
      "Canada Central",
      "Canada East",
      "Central India",
      "Central US",
      "East Asia",
      "East US",
      "East US 2",
      "France Central",
      "France South",
      "Germany North",
      "Germany West Central",
      "italy north",
      "Japan East",
      "Japan West",
      "Korea Central",
      "Korea South",
      "North Central US",
      "North Europe",
      "Norway East",
      "Norway West",
      "South Africa North",
      "South Africa West",
      "South Central US",
      "South India",
      "Southeast Asia",
      "Sweden Central",
      "Switzerland North",
      "Switzerland West",
      "UAE Central",
      "UAE North",
      "UK South",
      "UK West",
      "West Central US",
      "West Europe",
      "West US",
      "West US 2",
      "West US 3"
    ],
    "zoneMappings": []
  },
  {
    "aliases": null,
    "resourceType": "locations/workflows",
    "apiVersions": [
      "2022-09-01",
      "2022-06-01",
      "2020-09-01",
      "2020-03-01",
      "2019-10-01",
      "2019-06-01",
      "2019-03-01",
      "2019-02-01",
      "2018-10-01",
      "2018-07-01",
      "2018-04-02"
    ],
    "locations": [
      "Australia East",
      "Australia Southeast",
      "Brazil South",
      "Canada Central",
      "Canada East",
      "Central India",
      "Central US",
      "East Asia",
      "East US",
      "East US 2",
      "France Central",
      "France South",
      "Germany North",
      "Germany West Central",
      "italy north",
      "Japan East",
      "Japan West",
      "Korea Central",
      "Korea South",
      "North Central US",
      "North Europe",
      "Norway East",
      "Norway West",
      "South Africa North",
      "South Africa West",
      "South Central US",
      "South India",
      "Southeast Asia",
      "Sweden Central",
      "Switzerland North",
      "Switzerland West",
      "UAE Central",
      "UAE North",
      "UK South",
      "UK West",
      "West Central US",
      "West Europe",
      "West US",
      "West US 2",
      "West US 3"
    ],
    "zoneMappings": []
  },
  {
    "aliases": null,
    "resourceType": "operations",
    "apiVersions": [
      "2022-09-01",
      "2022-06-01",
      "2020-09-01",
      "2020-03-01",
      "2019-10-01",
      "2019-06-01",
      "2019-03-01",
      "2019-02-01",
      "2018-10-01",
      "2018-07-01",
      "2018-04-02"
    ],
    "locations": [
      "Australia East",
      "Australia Southeast",
      "Brazil South",
      "Canada Central",
      "Canada East",
      "Central India",
      "Central US",
      "East Asia",
      "East US",
      "East US 2",
      "France Central",
      "France South",
      "Germany North",
      "Germany West Central",
      "italy north",
      "Japan East",
      "Japan West",
      "Korea Central",
      "Korea South",
      "North Central US",
      "North Europe",
      "Norway East",
      "Norway West",
      "South Africa North",
      "South Africa West",
      "South Central US",
      "South India",
      "Southeast Asia",
      "Sweden Central",
      "Switzerland North",
      "Switzerland West",
      "UAE Central",
      "UAE North",
      "UK South",
      "UK West",
      "West Central US",
      "West Europe",
      "West US",
      "West US 2",
      "West US 3"
    ],
    "zoneMappings": []
  },
  {
    "aliases": {
      "Microsoft.StorageSync/storageSyncServices/incomingTrafficPolicy": "properties.incomingTrafficPolicy",
      "Microsoft.StorageSync/storageSyncServices/storageSyncServiceStatus": "properties.storageSyncServiceStatus",
      "Microsoft.StorageSync/storageSyncServices/storageSyncServiceUid": "properties.storageSyncServiceUid"
    },
    "resourceType": "storageSyncServices",
    "apiVersions": [
      "2022-09-01",
      "2022-06-01",
      "2020-09-01",
      "2020-03-01",
      "2019-10-01",
      "2019-06-01",
      "2019-03-01",
      "2019-02-01",
      "2018-10-01",
      "2018-07-01",
      "2018-04-02"
    ],
    "locations": [
      "Australia East",
      "Australia Southeast",
      "Brazil South",
      "Canada Central",
      "Canada East",
      "Central India",
      "Central US",
      "East Asia",
      "East US",
      "East US 2",
      "France Central",
      "France South",
      "Germany North",
      "Germany West Central",
      "italy north",
      "Japan East",
      "Japan West",
      "Korea Central",
      "Korea South",
      "North Central US",
      "North Europe",
      "Norway East",
      "Norway West",
      "South Africa North",
      "South Africa West",
      "South Central US",
      "South India",
      "Southeast Asia",
      "Sweden Central",
      "Switzerland North",
      "Switzerland West",
      "UAE Central",
      "UAE North",
      "UK South",
      "UK West",
      "West Central US",
      "West Europe",
      "West US",
      "West US 2",
      "West US 3"
    ],
    "zoneMappings": []
  },
  {
    "aliases": {
      "Microsoft.StorageSync/storageSyncServices/registeredServers/agentVersion": "properties.agentVersion",
      "Microsoft.StorageSync/storageSyncServices/registeredServers/clusterId": "properties.clusterId",
      "Microsoft.StorageSync/storageSyncServices/registeredServers/clusterName": "properties.clusterName",
      "Microsoft.StorageSync/storageSyncServices/registeredServers/friendlyName": "properties.friendlyName",
      "Microsoft.StorageSync/storageSyncServices/registeredServers/lastHeartBeat": "properties.lastHeartBeat",
      "Microsoft.StorageSync/storageSyncServices/registeredServers/lastWorkflowId": "properties.lastWorkflowId",
      "Microsoft.StorageSync/storageSyncServices/registeredServers/provisioningState": "properties.provisioningState",
      "Microsoft.StorageSync/storageSyncServices/registeredServers/serverCertificate": "properties.serverCertificate",
      "Microsoft.StorageSync/storageSyncServices/registeredServers/serverId": "properties.serverId",
      "Microsoft.StorageSync/storageSyncServices/registeredServers/serverManagementtErrorCode": "properties.serverManagementtErrorCode",
      "Microsoft.StorageSync/storageSyncServices/registeredServers/serverOSVersion": "properties.serverOSVersion",
      "Microsoft.StorageSync/storageSyncServices/registeredServers/serverRole": "properties.serverRole",
      "Microsoft.StorageSync/storageSyncServices/registeredServers/storageSyncServiceUid": "properties.storageSyncServiceUid"
    },
    "resourceType": "storageSyncServices/registeredServers",
    "apiVersions": [
      "2022-09-01",
      "2022-06-01",
      "2020-09-01",
      "2020-03-01",
      "2019-10-01",
      "2019-06-01",
      "2019-03-01",
      "2019-02-01",
      "2018-10-01",
      "2018-07-01",
      "2018-04-02"
    ],
    "locations": [
      "Australia East",
      "Australia Southeast",
      "Brazil South",
      "Canada Central",
      "Canada East",
      "Central India",
      "Central US",
      "East Asia",
      "East US",
      "East US 2",
      "France Central",
      "France South",
      "Germany North",
      "Germany West Central",
      "italy north",
      "Japan East",
      "Japan West",
      "Korea Central",
      "Korea South",
      "North Central US",
      "North Europe",
      "Norway East",
      "Norway West",
      "South Africa North",
      "South Africa West",
      "South Central US",
      "South India",
      "Southeast Asia",
      "Sweden Central",
      "Switzerland North",
      "Switzerland West",
      "UAE Central",
      "UAE North",
      "UK South",
      "UK West",
      "West Central US",
      "West Europe",
      "West US",
      "West US 2",
      "West US 3"
    ],
    "zoneMappings": []
  },
  {
    "aliases": {
      "Microsoft.StorageSync/storageSyncServices/syncGroups/syncGroupStatus": "properties.syncGroupStatus",
      "Microsoft.StorageSync/storageSyncServices/syncGroups/uniqueId": "properties.uniqueId"
    },
    "resourceType": "storageSyncServices/syncGroups",
    "apiVersions": [
      "2022-09-01",
      "2022-06-01",
      "2020-09-01",
      "2020-03-01",
      "2019-10-01",
      "2019-06-01",
      "2019-03-01",
      "2019-02-01",
      "2018-10-01",
      "2018-07-01",
      "2018-04-02"
    ],
    "locations": [
      "Australia East",
      "Australia Southeast",
      "Brazil South",
      "Canada Central",
      "Canada East",
      "Central India",
      "Central US",
      "East Asia",
      "East US",
      "East US 2",
      "France Central",
      "France South",
      "Germany North",
      "Germany West Central",
      "italy north",
      "Japan East",
      "Japan West",
      "Korea Central",
      "Korea South",
      "North Central US",
      "North Europe",
      "Norway East",
      "Norway West",
      "South Africa North",
      "South Africa West",
      "South Central US",
      "South India",
      "Southeast Asia",
      "Sweden Central",
      "Switzerland North",
      "Switzerland West",
      "UAE Central",
      "UAE North",
      "UK South",
      "UK West",
      "West Central US",
      "West Europe",
      "West US",
      "West US 2",
      "West US 3"
    ],
    "zoneMappings": []
  },
  {
    "aliases": {
      "Microsoft.StorageSync/storageSyncServices/syncGroups/cloudEndpoints/azureFileShareName": "properties.azureFileShareName",
      "Microsoft.StorageSync/storageSyncServices/syncGroups/cloudEndpoints/backupEnabled": "properties.backupEnabled",
      "Microsoft.StorageSync/storageSyncServices/syncGroups/cloudEndpoints/friendlyName": "properties.friendlyName",
      "Microsoft.StorageSync/storageSyncServices/syncGroups/cloudEndpoints/lastWorkflowId": "properties.lastWorkflowId",
      "Microsoft.StorageSync/storageSyncServices/syncGroups/cloudEndpoints/partnershipId": "properties.partnershipId",
      "Microsoft.StorageSync/storageSyncServices/syncGroups/cloudEndpoints/provisioningState": "properties.provisioningState",
      "Microsoft.StorageSync/storageSyncServices/syncGroups/cloudEndpoints/storageAccount": "properties.storageAccount",
      "Microsoft.StorageSync/storageSyncServices/syncGroups/cloudEndpoints/storageAccountKey": "properties.storageAccountKey",
      "Microsoft.StorageSync/storageSyncServices/syncGroups/cloudEndpoints/storageAccountResourceId": "properties.storageAccountResourceId",
      "Microsoft.StorageSync/storageSyncServices/syncGroups/cloudEndpoints/storageAccountShareName": "properties.storageAccountShareName",
      "Microsoft.StorageSync/storageSyncServices/syncGroups/cloudEndpoints/storageAccountTenantId": "properties.storageAccountTenantId"
    },
    "resourceType": "storageSyncServices/syncGroups/cloudEndpoints",
    "apiVersions": [
      "2022-09-01",
      "2022-06-01",
      "2020-09-01",
      "2020-03-01",
      "2019-10-01",
      "2019-06-01",
      "2019-03-01",
      "2019-02-01",
      "2018-10-01",
      "2018-07-01",
      "2018-04-02"
    ],
    "locations": [
      "Australia East",
      "Australia Southeast",
      "Brazil South",
      "Canada Central",
      "Canada East",
      "Central India",
      "Central US",
      "East Asia",
      "East US",
      "East US 2",
      "France Central",
      "France South",
      "Germany North",
      "Germany West Central",
      "italy north",
      "Japan East",
      "Japan West",
      "Korea Central",
      "Korea South",
      "North Central US",
      "North Europe",
      "Norway East",
      "Norway West",
      "South Africa North",
      "South Africa West",
      "South Central US",
      "South India",
      "Southeast Asia",
      "Sweden Central",
      "Switzerland North",
      "Switzerland West",
      "UAE Central",
      "UAE North",
      "UK South",
      "UK West",
      "West Central US",
      "West Europe",
      "West US",
      "West US 2",
      "West US 3"
    ],
    "zoneMappings": []
  },
  {
    "aliases": {
      "Microsoft.StorageSync/storageSyncServices/syncGroups/serverEndpoints/byteProgress": "properties.byteProgress",
      "Microsoft.StorageSync/storageSyncServices/syncGroups/serverEndpoints/byteTotal": "properties.byteTotal",
      "Microsoft.StorageSync/storageSyncServices/syncGroups/serverEndpoints/cloudTiering": "properties.cloudTiering",
      "Microsoft.StorageSync/storageSyncServices/syncGroups/serverEndpoints/currentProgressType": "properties.currentProgressType",
      "Microsoft.StorageSync/storageSyncServices/syncGroups/serverEndpoints/friendlyName": "properties.friendlyName",
      "Microsoft.StorageSync/storageSyncServices/syncGroups/serverEndpoints/initialDownloadPolicy": "properties.initialDownloadPolicy",
      "Microsoft.StorageSync/storageSyncServices/syncGroups/serverEndpoints/itemDownloadErrorCount": "properties.itemDownloadErrorCount",
      "Microsoft.StorageSync/storageSyncServices/syncGroups/serverEndpoints/itemProgressCount": "properties.itemProgressCount",
      "Microsoft.StorageSync/storageSyncServices/syncGroups/serverEndpoints/itemTotalCount": "properties.itemTotalCount",
      "Microsoft.StorageSync/storageSyncServices/syncGroups/serverEndpoints/itemUploadErrorCount": "properties.itemUploadErrorCount",
      "Microsoft.StorageSync/storageSyncServices/syncGroups/serverEndpoints/lastSyncSuccess": "properties.lastSyncSuccess",
      "Microsoft.StorageSync/storageSyncServices/syncGroups/serverEndpoints/lastWorkflowId": "properties.lastWorkflowId",
      "Microsoft.StorageSync/storageSyncServices/syncGroups/serverEndpoints/localCacheMode": "properties.localCacheMode",
      "Microsoft.StorageSync/storageSyncServices/syncGroups/serverEndpoints/offlineDataTransfer": "properties.offlineDataTransfer",
      "Microsoft.StorageSync/storageSyncServices/syncGroups/serverEndpoints/offlineDataTransferShareName": "properties.offlineDataTransferShareName",
      "Microsoft.StorageSync/storageSyncServices/syncGroups/serverEndpoints/provisioningState": "properties.provisioningState",
      "Microsoft.StorageSync/storageSyncServices/syncGroups/serverEndpoints/serverLocalPath": "properties.serverLocalPath",
      "Microsoft.StorageSync/storageSyncServices/syncGroups/serverEndpoints/serverResourceId": "properties.serverResourceId",
      "Microsoft.StorageSync/storageSyncServices/syncGroups/serverEndpoints/syncErrorContext": "properties.syncErrorContext",
      "Microsoft.StorageSync/storageSyncServices/syncGroups/serverEndpoints/syncErrorDirection": "properties.syncErrorDirection",
      "Microsoft.StorageSync/storageSyncServices/syncGroups/serverEndpoints/syncErrorState": "properties.syncErrorState",
      "Microsoft.StorageSync/storageSyncServices/syncGroups/serverEndpoints/syncErrorStateTimestamp": "properties.syncErrorStateTimestamp",
      "Microsoft.StorageSync/storageSyncServices/syncGroups/serverEndpoints/tierFilesOlderThanDays": "properties.tierFilesOlderThanDays",
      "Microsoft.StorageSync/storageSyncServices/syncGroups/serverEndpoints/totalProgress": "properties.totalProgress",
      "Microsoft.StorageSync/storageSyncServices/syncGroups/serverEndpoints/volumeFreeSpacePercent": "properties.volumeFreeSpacePercent"
    },
    "resourceType": "storageSyncServices/syncGroups/serverEndpoints",
    "apiVersions": [
      "2022-09-01",
      "2022-06-01",
      "2020-09-01",
      "2020-03-01",
      "2019-10-01",
      "2019-06-01",
      "2019-03-01",
      "2019-02-01",
      "2018-10-01",
      "2018-07-01",
      "2018-04-02"
    ],
    "locations": [
      "Australia East",
      "Australia Southeast",
      "Brazil South",
      "Canada Central",
      "Canada East",
      "Central India",
      "Central US",
      "East Asia",
      "East US",
      "East US 2",
      "France Central",
      "France South",
      "Germany North",
      "Germany West Central",
      "italy north",
      "Japan East",
      "Japan West",
      "Korea Central",
      "Korea South",
      "North Central US",
      "North Europe",
      "Norway East",
      "Norway West",
      "South Africa North",
      "South Africa West",
      "South Central US",
      "South India",
      "Southeast Asia",
      "Sweden Central",
      "Switzerland North",
      "Switzerland West",
      "UAE Central",
      "UAE North",
      "UK South",
      "UK West",
      "West Central US",
      "West Europe",
      "West US",
      "West US 2",
      "West US 3"
    ],
    "zoneMappings": []
  },
  {
    "aliases": null,
    "resourceType": "storageSyncServices/workflows",
    "apiVersions": [
      "2022-09-01",
      "2022-06-01",
      "2020-09-01",
      "2020-03-01",
      "2019-10-01",
      "2019-06-01",
      "2019-03-01",
      "2019-02-01",
      "2018-10-01",
      "2018-07-01",
      "2018-04-02"
    ],
    "locations": [
      "Australia East",
      "Australia Southeast",
      "Brazil South",
      "Canada Central",
      "Canada East",
      "Central India",
      "Central US",
      "East Asia",
      "East US",
      "East US 2",
      "France Central",
      "France South",
      "Germany North",
      "Germany West Central",
      "italy north",
      "Japan East",
      "Japan West",
      "Korea Central",
      "Korea South",
      "North Central US",
      "North Europe",
      "Norway East",
      "Norway West",
      "South Africa North",
      "South Africa West",
      "South Central US",
      "South India",
      "Southeast Asia",
      "Sweden Central",
      "Switzerland North",
      "Switzerland West",
      "UAE Central",
      "UAE North",
      "UK South",
      "UK West",
      "West Central US",
      "West Europe",
      "West US",
      "West US 2",
      "West US 3"
    ],
    "zoneMappings": []
  },
  {
    "aliases": {
      "Microsoft.StorageSync/storageSyncServices/privateEndpointConnections/privateEndpoint": "properties.privateEndpoint",
      "Microsoft.StorageSync/storageSyncServices/privateEndpointConnections/privateEndpoint.id": "properties.privateEndpoint.id",
      "Microsoft.StorageSync/storageSyncServices/privateEndpointConnections/privateLinkServiceConnectionState": "properties.privateLinkServiceConnectionState",
      "Microsoft.StorageSync/storageSyncServices/privateEndpointConnections/privateLinkServiceConnectionState.actionRequired": "properties.privateLinkServiceConnectionState.actionRequired",
      "Microsoft.StorageSync/storageSyncServices/privateEndpointConnections/privateLinkServiceConnectionState.actionsRequired": "properties.privateLinkServiceConnectionState.actionsRequired",
      "Microsoft.StorageSync/storageSyncServices/privateEndpointConnections/privateLinkServiceConnectionState.description": "properties.privateLinkServiceConnectionState.description",
      "Microsoft.StorageSync/storageSyncServices/privateEndpointConnections/privateLinkServiceConnectionState.status": "properties.privateLinkServiceConnectionState.status",
      "Microsoft.StorageSync/storageSyncServices/privateEndpointConnections/provisioningState": "properties.provisioningState"
    },
    "resourceType": "storagesyncservices/privateendpointconnections"
  }
]
