[
  {
    "aliases": null,
    "resourceType": "instances",
    "apiVersions": [
      "2025-04-01",
      "2024-11-01",
      "2024-09-15-preview",
      "2024-08-15-preview",
      "2024-07-01-preview"
    ],
    "locations": [
      "East US",
      "East US 2",
      "North Europe",
      "West Europe",
      "West US",
      "West US 2",
      "West US 3"
    ],
    "zoneMappings": []
  },
  {
    "aliases": null,
    "resourceType": "instances/brokers",
    "apiVersions": [
      "2025-04-01",
      "2024-11-01",
      "2024-09-15-preview",
      "2024-08-15-preview",
      "2024-07-01-preview"
    ],
    "locations": [
      "East US",
      "East US 2",
      "North Europe",
      "West Europe",
      "West US",
      "West US 2",
      "West US 3"
    ],
    "zoneMappings": []
  },
  {
    "aliases": null,
    "resourceType": "instances/brokers/authentications",
    "apiVersions": [
      "2025-04-01",
      "2024-11-01",
      "2024-09-15-preview",
      "2024-08-15-preview",
      "2024-07-01-preview"
    ],
    "locations": [
      "East US",
      "East US 2",
      "North Europe",
      "West Europe",
      "West US",
      "West US 2",
      "West US 3"
    ],
    "zoneMappings": []
  },
  {
    "aliases": null,
    "resourceType": "instances/brokers/authorizations",
    "apiVersions": [
      "2025-04-01",
      "2024-11-01",
      "2024-09-15-preview",
      "2024-08-15-preview",
      "2024-07-01-preview",
      "2024-06-01-preview"
    ],
    "locations": [
      "East US",
      "East US 2",
      "North Europe",
      "West Europe",
      "West US",
      "West US 2",
      "West US 3"
    ],
    "zoneMappings": []
  },
  {
    "aliases": null,
    "resourceType": "instances/brokers/listeners",
    "apiVersions": [
      "2025-04-01",
      "2024-11-01",
      "2024-09-15-preview",
      "2024-08-15-preview",
      "2024-07-01-preview"
    ],
    "locations": [
      "East US",
      "East US 2",
      "North Europe",
      "West Europe",
      "West US",
      "West US 2",
      "West US 3"
    ],
    "zoneMappings": []
  },
  {
    "aliases": null,
    "resourceType": "instances/dataflowEndpoints",
    "apiVersions": [
      "2025-04-01",
      "2024-11-01",
      "2024-09-15-preview",
      "2024-08-15-preview",
      "2024-07-01-preview"
    ],
    "locations": [
      "East US",
      "East US 2",
      "North Europe",
      "West Europe",
      "West US",
      "West US 2",
      "West US 3"
    ],
    "zoneMappings": []
  },
  {
    "aliases": null,
    "resourceType": "instances/dataflowProfiles",
    "apiVersions": [
      "2025-04-01",
      "2024-11-01",
      "2024-09-15-preview",
      "2024-08-15-preview",
      "2024-07-01-preview"
    ],
    "locations": [
      "East US",
      "East US 2",
      "North Europe",
      "West Europe",
      "West US",
      "West US 2",
      "West US 3"
    ],
    "zoneMappings": []
  },
  {
    "aliases": null,
    "resourceType": "instances/dataflowProfiles/dataflows",
    "apiVersions": [
      "2025-04-01",
      "2024-11-01",
      "2024-09-15-preview",
      "2024-08-15-preview",
      "2024-07-01-preview"
    ],
    "locations": [
      "East US",
      "East US 2",
      "North Europe",
      "West Europe",
      "West US",
      "West US 2",
      "West US 3"
    ],
    "zoneMappings": []
  },
  {
    "aliases": null,
    "resourceType": "locations",
    "apiVersions": [
      "2025-04-01",
      "2024-11-01",
      "2024-09-15-preview",
      "2024-08-15-preview",
      "2024-07-01-preview"
    ],
    "locations": [
      "global"
    ],
    "zoneMappings": []
  },
  {
    "aliases": null,
    "resourceType": "locations/operationStatuses",
    "apiVersions": [
      "2025-04-01",
      "2024-11-01",
      "2024-09-15-preview",
      "2024-08-15-preview",
      "2024-07-01-preview"
    ],
    "locations": [
      "East US",
      "East US 2",
      "North Europe",
      "West Europe",
      "West US",
      "West US 2",
      "West US 3"
    ],
    "zoneMappings": []
  },
  {
    "aliases": null,
    "resourceType": "operations",
    "apiVersions": [
      "2025-04-01",
      "2024-11-01",
      "2024-09-15-preview",
      "2024-08-15-preview",
      "2024-07-01-preview"
    ],
    "locations": [],
    "zoneMappings": []
  }
]
