{
  "$schema": "https://schema.management.azure.com/schemas/2019-04-01/deploymentTemplate.json#",
  "contentVersion": "1.0.0.0",
  "metadata": {
    "_generator": {
      "name": "bicep",
      "version": "0.6.18.56646",
      "templateHash": "18260890349087263285"
    }
  },
  "parameters": {
    "name": {
      "type": "string",
      "metadata": {
        "description": "The name of the resource."
      }
    },
    "location": {
      "type": "string",
      "defaultValue": "[resourceGroup().location]",
      "metadata": {
        "description": "The location resources will be deployed."
      }
    }
  },
  "resources": [
    {
      "type": "Microsoft.KeyVault/vaults",
      "apiVersion": "2021-10-01",
      "name": "[parameters('name')]",
      "location": "[parameters('location')]",
      "properties": {
        "sku": {
          "family": "A",
          "name": "premium"
        },
        "tenantId": "[subscription().tenantId]",
        "enableSoftDelete": true,
        "softDeleteRetentionInDays": 90,
        "enablePurgeProtection": true
      }
    }
  ]
}